glu_tf/__init__.py
glu_tf/glu.py
glu_tf/version.py
GLU_tf-0.1.0.dist-info/LICENSE
GLU_tf-0.1.0.dist-info/METADATA
GLU_tf-0.1.0.dist-info/WHEEL
GLU_tf-0.1.0.dist-info/top_level.txt
GLU_tf-0.1.0.dist-info/RECORD
